invoice/__init__.py
invoice/invoice.py
invoice-1.0.1.dist-info/LICENSE
invoice-1.0.1.dist-info/METADATA
invoice-1.0.1.dist-info/WHEEL
invoice-1.0.1.dist-info/top_level.txt
invoice-1.0.1.dist-info/RECORD
