Metadata-Version: 2.1
Name: invoice
Version: 1.0.1
Summary: 中華民國財政部統一發票
Home-page: https://github.com/as209099/invoice-python-lib
Author: as209099
Author-email: as209099@gmail.com
License: MIT
Platform: UNKNOWN
Classifier: Programming Language :: Python :: 3.6
Classifier: Programming Language :: Python :: 3.7
Classifier: Programming Language :: Python :: 3.8
Classifier: Programming Language :: Python :: 3.9
Classifier: Programming Language :: Python :: 3.10
Classifier: License :: OSI Approved :: MIT License
Classifier: Operating System :: OS Independent
Requires-Python: >=3.6
License-File: LICENSE
